AUTHORS.rst
LICENSE
MANIFEST.in
README.rst
setup.cfg
setup.py
freezegun/__init__.py
freezegun/api.py
freezegun_vinta.egg-info/PKG-INFO
freezegun_vinta.egg-info/SOURCES.txt
freezegun_vinta.egg-info/dependency_links.txt
freezegun_vinta.egg-info/requires.txt
freezegun_vinta.egg-info/top_level.txt
tests/__init__.py
tests/another_module.py
tests/fake_module.py
tests/test_class_import.py
tests/test_datetimes.py
tests/test_import_alias.py
tests/test_operations.py
tests/test_pickle.py
tests/test_sqlite3.py
tests/test_ticking.py
tests/test_utils.py
tests/utils.py