Metadata-Version: 1.1
Name: freezegun-vinta
Version: 0.3.7.1
Summary: Let your Python tests travel through time
Home-page: https://github.com/spulec/freezegun
Author: Steve Pulec
Author-email: spulec@gmail
License: Apache 2.0
Platform: UNKNOWN
Classifier: License :: OSI Approved :: Apache Software License
Classifier: Programming Language :: Python :: 2
Classifier: Programming Language :: Python :: 2.6
Classifier: Programming Language :: Python :: 2.7
Classifier: Programming Language :: Python :: 3
Classifier: Programming Language :: Python :: 3.3
